dynect
