Metadata-Version: 1.0
Name: dynect
Version: 0.0.7
Summary: Wrapper library to Dynect API.
Home-page: http://github.com/jorgeecardona/dynect
Author: Jorge Eduardo Cardona
Author-email: jorgeecardona@gmail.com
License: UNKNOWN
Platform: UNKNOWN
